LICENSE
nxv/__init__.py
nxv/_functional.py
nxv/_graphviz.py
nxv/_ipython.py
nxv/_rendering.py
nxv/_style.py
nxv/_util.py
nxv/html_like/__init__.py
nxv/html_like/_html_like.py
nxv/styles/__init__.py
nxv/styles/_font.py
nxv/styles/_verbose.py
nxv-0.1.3.dist-info/LICENSE
nxv-0.1.3.dist-info/WHEEL
nxv-0.1.3.dist-info/METADATA
nxv-0.1.3.dist-info/RECORD
