Metadata-Version: 2.1
Name: nxv
Version: 0.1.3
Summary: Render NetworkX graphs using GraphViz
Home-page: https://github.com/twosigma/nxv
License: Apache-2.0
Keywords: networkx,graphviz,graph,tree,network,draw,render,visualize,visualization
Author: Timothy Shields
Author-email: Timothy.Shields@twosigma.com
Requires-Python: >=3.6,<4.0
Classifier: License :: OSI Approved :: Apache Software License
Classifier: Programming Language :: Python :: 3
Classifier: Programming Language :: Python :: 3.6
Classifier: Programming Language :: Python :: 3.7
Classifier: Programming Language :: Python :: 3.8
Requires-Dist: networkx (>=2.5,<3.0)
Project-URL: Documentation, https://nxv.readthedocs.io/
Project-URL: Repository, https://github.com/twosigma/nxvz
